Browser/__init__.py
Browser/assertion_engine.py
Browser/browser.py
Browser/browser.pyi
Browser/gen_stub.py
Browser/playwright.py
Browser/version.py
Browser/base/__init__.py
Browser/base/cache.py
Browser/base/librarycomponent.py
Browser/entry/__init__.py
Browser/entry/__main__.py
Browser/entry/constant.py
Browser/entry/coverage_combine.py
Browser/entry/get_versions.py
Browser/entry/rfbrowser_init.py
Browser/entry/transform.py
Browser/entry/translation.py
Browser/generated/__init__.py
Browser/generated/playwright_pb2.py
Browser/generated/playwright_pb2.pyi
Browser/generated/playwright_pb2_grpc.py
Browser/keywords/__init__.py
Browser/keywords/assertion_formatter.py
Browser/keywords/browser_control.py
Browser/keywords/clock.py
Browser/keywords/cookie.py
Browser/keywords/coverage.py
Browser/keywords/crawling.py
Browser/keywords/device_descriptors.py
Browser/keywords/evaluation.py
Browser/keywords/getters.py
Browser/keywords/interaction.py
Browser/keywords/locator_handler.py
Browser/keywords/network.py
Browser/keywords/pdf.py
Browser/keywords/playwright_state.py
Browser/keywords/promises.py
Browser/keywords/runonfailure.py
Browser/keywords/strict_mode.py
Browser/keywords/waiter.py
Browser/keywords/webapp_state.py
Browser/robocop_transformer/__init__.py
Browser/robocop_transformer/network_idle.py
Browser/utils/__init__.py
Browser/utils/data_types.py
Browser/utils/deprecated.py
Browser/utils/js_utilities.py
Browser/utils/logger.py
Browser/utils/meta_python.py
Browser/utils/misc.py
Browser/utils/robot_booleans.py
Browser/utils/settings_stack.py
Browser/wrapper/index.js
Browser/wrapper/package-lock.json
Browser/wrapper/package.json
Browser/wrapper/static/selector-finder.js
mypy_stub/Browser/__init__.pyi
mypy_stub/Browser/assertion_engine.pyi
mypy_stub/Browser/browser.pyi
mypy_stub/Browser/gen_stub.pyi
mypy_stub/Browser/playwright.pyi
mypy_stub/Browser/version.pyi
mypy_stub/Browser/base/__init__.pyi
mypy_stub/Browser/base/cache.pyi
mypy_stub/Browser/base/librarycomponent.pyi
robotframework_browser-19.12.4.dist-info/licenses/LICENSE
robotframework_browser-19.12.4.dist-info/METADATA
robotframework_browser-19.12.4.dist-info/WHEEL
robotframework_browser-19.12.4.dist-info/entry_points.txt
robotframework_browser-19.12.4.dist-info/top_level.txt
robotframework_browser-19.12.4.dist-info/RECORD
