Metadata-Version: 2.4
Name: robotframework-browser
Version: 19.12.4
Summary: Robot Framework Browser library powered by Playwright. Aiming for speed, reliability and visibility.
Author: MarketSquare - Robot Framework community
Maintainer-email: Tatu Aalto <aalto.aalto@gmail.com>, Mikko Korpela <mikko.korpela@gmail.com>, Kerkko Pelttari <kerk.pelt@gmail.com>, René Rohner <rene@robotframework.org>
License-Expression: Apache-2.0
Project-URL: Homepage, https://robotframework-browser.org/
Project-URL: Documentation, https://marketsquare.github.io/robotframework-browser/Browser.html
Project-URL: Repository, https://github.com/MarketSquare/robotframework-browser
Project-URL: Issues, https://github.com/MarketSquare/robotframework-browser/issues
Project-URL: Changelog, https://github.com/MarketSquare/robotframework-browser/tree/main/docs/releasenotes
Keywords: robotframework,playwright,testing,automation,web,browser
Classifier: Development Status :: 5 - Production/Stable
Classifier: Operating System :: OS Independent
Classifier: Programming Language :: Python :: 3
Classifier: Topic :: Software Development :: Testing
Classifier: Framework :: Robot Framework
Classifier: Framework :: Robot Framework :: Library
Requires-Python: >=3.10
License-File: LICENSE
Requires-Dist: grpcio==1.76.0
Requires-Dist: grpcio-tools==1.76.0
Requires-Dist: protobuf==6.33.5
Requires-Dist: robotframework<9.0.0,>=6.1.1
Requires-Dist: robotframework-pythonlibcore<5.0.0,>=4.4.1
Requires-Dist: robotframework-assertion-engine<4.0.0,>=3.1.3
Requires-Dist: wrapt>=2.0.1
Requires-Dist: overrides>=7.7.0
Requires-Dist: click>=8.1.8
Requires-Dist: seedir>=0.5.1
Requires-Dist: psutil>=7.1.3
Requires-Dist: PyYAML>=6.0.3
Provides-Extra: robocop
Requires-Dist: robotframework-robocop>=6.10.0; extra == "robocop"
Provides-Extra: bb
Requires-Dist: robotframework-browser-batteries>=19.7.2; extra == "bb"
Dynamic: license-file
